flask_stripe_checkout/__init__.py
flask_stripe_checkout/cart.py
flask_stripe_checkout/cart_blueprint.py
flask_stripe_checkout/subscription.py
flask_stripe_checkout/templates/cart/cart.html
flask_stripe_checkout/templates/cart/cart_page.html
flask_stripe_checkout/templates/cart/checkout_success.html
flask_stripe_checkout/templates/cart/layout.html
flask_stripe_checkout/webhooks.py
flask_stripe_checkout-0.1.0.dist-info/LICENSE
flask_stripe_checkout-0.1.0.dist-info/METADATA
flask_stripe_checkout-0.1.0.dist-info/WHEEL
flask_stripe_checkout-0.1.0.dist-info/RECORD
