Metadata-Version: 2.1
Name: flask-stripe-checkout
Version: 0.1.0
Summary: 
Home-page: https://github.com/hyperflask/flask-stripe-checkout
License: MIT
Author: Maxime Bouroumeau-Fuseau
Author-email: maxime.bouroumeau@gmail.com
Requires-Python: >=3.8,<4.0
Classifier: License :: OSI Approved :: MIT License
Classifier: Programming Language :: Python :: 3
Classifier: Programming Language :: Python :: 3.8
Classifier: Programming Language :: Python :: 3.9
Classifier: Programming Language :: Python :: 3.10
Classifier: Programming Language :: Python :: 3.11
Classifier: Programming Language :: Python :: 3.12
Requires-Dist: flask (>=3.0.1,<4.0.0)
Requires-Dist: stripe (>=8.0.0,<9.0.0)
Project-URL: Repository, https://github.com/hyperflask/flask-stripe-checkout
